sparkml_base_classes/__init__.py
sparkml_base_classes/sparkml_base_classes.py
sparkml_base_classes-0.1.6.dist-info/WHEEL
sparkml_base_classes-0.1.6.dist-info/METADATA
sparkml_base_classes-0.1.6.dist-info/RECORD
