Metadata-Version: 2.1
Name: sparkml-base-classes
Version: 0.1.6
Summary: SparkML base classes for Transformers and Estimators
Author: Rodrigo Agundez
Author-email: rragundez@gmail.com
Requires-Python: >=3.9,<4.0
Classifier: Programming Language :: Python :: 3
Classifier: Programming Language :: Python :: 3.9
Classifier: Programming Language :: Python :: 3.10
Classifier: Programming Language :: Python :: 3.11
